pushikoo_getter_gh/__init__.py
pushikoo_getter_gh/api.py
pushikoo_getter_gh/config.py
pushikoo_getter_gh/main.py
pushikoo_getter_gh-0.1.2.dist-info/METADATA
pushikoo_getter_gh-0.1.2.dist-info/WHEEL
pushikoo_getter_gh-0.1.2.dist-info/entry_points.txt
pushikoo_getter_gh-0.1.2.dist-info/licenses/LICENSE
pushikoo_getter_gh-0.1.2.dist-info/RECORD
