Metadata-Version: 2.4
Name: pushikoo-getter-gh
Version: 0.1.2
Summary: GitHub getter adapter for Pushikoo.
Project-URL: Homepage, https://github.com/Pushikoo/pushikoo-getter-gh
Author: Pushikoo
License-File: LICENSE
Classifier: Operating System :: OS Independent
Classifier: Programming Language :: Python :: 3
Requires-Python: >=3.10
Requires-Dist: loguru
Requires-Dist: pushikoo-interface>=0.2.0
Requires-Dist: python-dateutil
Requires-Dist: requests
Provides-Extra: dev
Requires-Dist: pytest; extra == 'dev'
Requires-Dist: python-dotenv; extra == 'dev'
Requires-Dist: ruff; extra == 'dev'
